cli/__init__.py
cli/auto_complete.py
cli/cli.py
cli/cmds/__init__.py
cli/cmds/cmd_dump.py
cli/cmds/config.py
cli/cmds/delete.py
cli/cmds/download.py
cli/cmds/get.py
cli/cmds/kill.py
cli/cmds/login.py
cli/cmds/pd.py
cli/cmds/rec.py
cli/cmds/run.py
cli/cmds/set_env.py
cli/cmds/set_log_level.py
cli/cmds/version.py
cli/deploy.py
cli/helpers.py
cli/interactive.py
common/__init__.py
common/api/__init__.py
common/api/create_job.py
common/api/delete_job.py
common/api/error_model.py
common/api/funding_envs_images.py
common/api/get_env_rec.py
common/api/get_job.py
common/api/get_pd_auth.py
common/api/list_jobs.py
common/api/login.py
common/api/presigned_url.py
common/api/start_job.py
common/api/stream_logs.py
common/api/terminate_job.py
common/api/validate_user_auth_token.py
common/aws/__init__.py
common/aws/s3.py
common/build_env
common/build_env.py
common/cli_args.py
common/common_dump.py
common/config.py
common/console.py
common/constants.py
common/custom_file_filter.py
common/enums.py
common/env_config.py
common/env_defaults.py
common/exceptions.py
common/image_name.py
common/job.py
common/local_container.py
common/logging_config.py
common/matplotlib_inline/__init__.py
common/matplotlib_inline/backend_inline.py
common/observability/__init__.py
common/observability/main.py
common/print_banner.py
common/tests/test_build_env.py
common/user_config.py
common/utils.py
common/validation.py
positron_job_runner/__init__.py
positron_job_runner/bootstrap_runtime_environment.py
positron_job_runner/cli.py
positron_job_runner/cloud_logger.py
positron_job_runner/cloud_storage.py
positron_job_runner/cloudwatch_client.py
positron_job_runner/lil_byter.py
positron_job_runner/logging_config.py
positron_job_runner/remote_function.py
positron_job_runner/run_job.py
positron_job_runner/runner_env.py
positron_job_runner/runtime_environment_manager.py
positron_job_runner/s3_client.py
positron_job_runner/workspace.py
remote_function/__init__.py
remote_function/deploy.py
robbie-0.1.44.dist-info/LICENSE
robbie-0.1.44.dist-info/METADATA
robbie-0.1.44.dist-info/WHEEL
robbie-0.1.44.dist-info/entry_points.txt
robbie-0.1.44.dist-info/RECORD
